{
  "extremes": {
    "hottest": {
      "name": "Singapore",
      "lat": 1.3521,
      "lon": 103.8198,
      "country": "Singapore",
      "temp": 29.71,
      "tempYesterday": 29.870358459654714,
      "tempSwing": 1.8099999999999987,
      "windSpeed": 2.57,
      "humidity": 78,
      "feelsLike": 36.27,
      "rainfall24h": 0,
      "pressure": 1012
    },
    "coldest": {
      "name": "Vostok Station",
      "lat": -78.4645,
      "lon": 106.8374,
      "country": "Antarctica",
      "temp": -34.78,
      "tempYesterday": -33.65412777498082,
      "tempSwing": 11.547253800934689,
      "windSpeed": 4.13,
      "humidity": 99,
      "feelsLike": -41.78,
      "rainfall24h": 0,
      "pressure": 1015
    },
    "windiest": {
      "name": "Barrow",
      "lat": 71.2906,
      "lon": -156.7886,
      "country": "USA",
      "temp": -4.99,
      "tempYesterday": -7.381752579274343,
      "tempSwing": 3.941665517647976,
      "windSpeed": 9.77,
      "humidity": 86,
      "feelsLike": -11.99,
      "rainfall24h": 0,
      "pressure": 999
    },
    "mostHumid": {
      "name": "Vostok Station",
      "lat": -78.4645,
      "lon": 106.8374,
      "country": "Antarctica",
      "temp": -34.78,
      "tempYesterday": -33.65412777498082,
      "tempSwing": 11.547253800934689,
      "windSpeed": 4.13,
      "humidity": 99,
      "feelsLike": -41.78,
      "rainfall24h": 0,
      "pressure": 1015
    },
    "biggestSwing": {
      "name": "Commonwealth Bay",
      "lat": -67,
      "lon": 142.6667,
      "country": "Antarctica",
      "temp": -6.95,
      "tempYesterday": -7.1766931012755535,
      "tempSwing": 11.866127502542474,
      "windSpeed": 7.7,
      "humidity": 45,
      "feelsLike": -13.95,
      "rainfall24h": 0,
      "pressure": 984
    },
    "mostRain": {
      "name": "Death Valley",
      "lat": 36.5323,
      "lon": -116.9325,
      "country": "USA",
      "temp": 26.77,
      "tempYesterday": 25.79958037285509,
      "tempSwing": 3.616360396717297,
      "windSpeed": 0.24,
      "humidity": 15,
      "feelsLike": 25.81,
      "rainfall24h": 0,
      "pressure": 1015
    },
    "lowestPressure": {
      "name": "Commonwealth Bay",
      "lat": -67,
      "lon": 142.6667,
      "country": "Antarctica",
      "temp": -6.95,
      "tempYesterday": -7.1766931012755535,
      "tempSwing": 11.866127502542474,
      "windSpeed": 7.7,
      "humidity": 45,
      "feelsLike": -13.95,
      "rainfall24h": 0,
      "pressure": 984
    }
  },
  "allLocations": [
    {
      "name": "Death Valley",
      "lat": 36.5323,
      "lon": -116.9325,
      "country": "USA",
      "temp": 26.77,
      "tempYesterday": 25.79958037285509,
      "tempSwing": 3.616360396717297,
      "windSpeed": 0.24,
      "humidity": 15,
      "feelsLike": 25.81,
      "rainfall24h": 0,
      "pressure": 1015
    },
    {
      "name": "Dallol",
      "lat": 14.2417,
      "lon": 40.2833,
      "country": "Ethiopia",
      "temp": 28.75,
      "tempYesterday": 30.693103076308514,
      "tempSwing": 6.611733513768844,
      "windSpeed": 6,
      "humidity": 54,
      "feelsLike": 29.82,
      "rainfall24h": 0,
      "pressure": 1012
    },
    {
      "name": "Kuwait City",
      "lat": 29.3759,
      "lon": 47.9774,
      "country": "Kuwait",
      "temp": 22.09,
      "tempYesterday": 20.849320703661007,
      "tempSwing": 5.885236544937109,
      "windSpeed": 6.42,
      "humidity": 25,
      "feelsLike": 21.01,
      "rainfall24h": 0,
      "pressure": 1016
    },
    {
      "name": "Ahvaz",
      "lat": 31.3183,
      "lon": 48.6706,
      "country": "Iran",
      "temp": 16,
      "tempYesterday": 15.24277885691506,
      "tempSwing": 7.077235973950395,
      "windSpeed": 2.06,
      "humidity": 31,
      "feelsLike": 14.47,
      "rainfall24h": 0,
      "pressure": 1015
    },
    {
      "name": "Aswan",
      "lat": 24.0889,
      "lon": 32.8998,
      "country": "Egypt",
      "temp": 25.58,
      "tempYesterday": 27.352506315330782,
      "tempSwing": 6.657938926504729,
      "windSpeed": 0,
      "humidity": 41,
      "feelsLike": 25.26,
      "rainfall24h": 0,
      "pressure": 1011
    },
    {
      "name": "Luxor",
      "lat": 25.6872,
      "lon": 32.6396,
      "country": "Egypt",
      "temp": 22.03,
      "tempYesterday": 22.216317028069113,
      "tempSwing": 4.552174221661189,
      "windSpeed": 1.54,
      "humidity": 49,
      "feelsLike": 21.57,
      "rainfall24h": 0,
      "pressure": 1012
    },
    {
      "name": "Vostok Station",
      "lat": -78.4645,
      "lon": 106.8374,
      "country": "Antarctica",
      "temp": -34.78,
      "tempYesterday": -33.65412777498082,
      "tempSwing": 11.547253800934689,
      "windSpeed": 4.13,
      "humidity": 99,
      "feelsLike": -41.78,
      "rainfall24h": 0,
      "pressure": 1015
    },
    {
      "name": "Oymyakon",
      "lat": 63.4608,
      "lon": 142.7858,
      "country": "Russia",
      "temp": -22.71,
      "tempYesterday": -22.908676461131677,
      "tempSwing": 8.46932617634349,
      "windSpeed": 0.92,
      "humidity": 92,
      "feelsLike": -22.71,
      "rainfall24h": 0,
      "pressure": 1018
    },
    {
      "name": "Verkhoyansk",
      "lat": 67.5447,
      "lon": 133.385,
      "country": "Russia",
      "temp": -17.64,
      "tempYesterday": -15.787368112608089,
      "tempSwing": 7.4989038059421755,
      "windSpeed": 0.63,
      "humidity": 96,
      "feelsLike": -17.64,
      "rainfall24h": 0,
      "pressure": 1018
    },
    {
      "name": "Yakutsk",
      "lat": 62.0355,
      "lon": 129.6755,
      "country": "Russia",
      "temp": -14.07,
      "tempYesterday": -15.086803645241414,
      "tempSwing": 8.324659905935313,
      "windSpeed": 1,
      "humidity": 78,
      "feelsLike": -14.07,
      "rainfall24h": 0,
      "pressure": 1020
    },
    {
      "name": "Eureka",
      "lat": 79.9833,
      "lon": -85.9333,
      "country": "Canada",
      "temp": -25.89,
      "tempYesterday": -24.757021511081987,
      "tempSwing": 10.128125092806396,
      "windSpeed": 1.54,
      "humidity": 76,
      "feelsLike": -31.4,
      "rainfall24h": 0,
      "pressure": 1013
    },
    {
      "name": "Mount Washington",
      "lat": 44.2706,
      "lon": -71.3033,
      "country": "USA",
      "temp": -7.53,
      "tempYesterday": -5.942246871370937,
      "tempSwing": 1.7800000000000002,
      "windSpeed": 3.81,
      "humidity": 78,
      "feelsLike": -13.36,
      "rainfall24h": 0,
      "pressure": 1016
    },
    {
      "name": "Commonwealth Bay",
      "lat": -67,
      "lon": 142.6667,
      "country": "Antarctica",
      "temp": -6.95,
      "tempYesterday": -7.1766931012755535,
      "tempSwing": 11.866127502542474,
      "windSpeed": 7.7,
      "humidity": 45,
      "feelsLike": -13.95,
      "rainfall24h": 0,
      "pressure": 984
    },
    {
      "name": "Mawsynram",
      "lat": 25.2977,
      "lon": 91.5819,
      "country": "India",
      "temp": 20.85,
      "tempYesterday": 19.358146324643094,
      "tempSwing": 3.8027433924652594,
      "windSpeed": 0.83,
      "humidity": 92,
      "feelsLike": 21.39,
      "rainfall24h": 0,
      "pressure": 1012
    },
    {
      "name": "Cherrapunji",
      "lat": 25.2677,
      "lon": 91.7322,
      "country": "India",
      "temp": 16.66,
      "tempYesterday": 18.647782669228853,
      "tempSwing": 3.7354358683619777,
      "windSpeed": 0.48,
      "humidity": 93,
      "feelsLike": 16.81,
      "rainfall24h": 0,
      "pressure": 1012
    },
    {
      "name": "Atacama Desert",
      "lat": -23.8501,
      "lon": -69.2483,
      "country": "Chile",
      "temp": 13.61,
      "tempYesterday": 13.590727666825874,
      "tempSwing": 9.767883390025837,
      "windSpeed": 1.71,
      "humidity": 17,
      "feelsLike": 11.47,
      "rainfall24h": 0,
      "pressure": 1017
    },
    {
      "name": "Arica",
      "lat": -18.4783,
      "lon": -70.3126,
      "country": "Chile",
      "temp": 18.16,
      "tempYesterday": 20.257020577125033,
      "tempSwing": 5.758932478219007,
      "windSpeed": 1.54,
      "humidity": 72,
      "feelsLike": 17.91,
      "rainfall24h": 0,
      "pressure": 1017
    },
    {
      "name": "La Rinconada",
      "lat": -14.6333,
      "lon": -69.45,
      "country": "Peru",
      "temp": 1.77,
      "tempYesterday": 2.785135127811179,
      "tempSwing": 10.017179586305971,
      "windSpeed": 0.73,
      "humidity": 85,
      "feelsLike": 1.77,
      "rainfall24h": 0,
      "pressure": 1021
    },
    {
      "name": "Barrow",
      "lat": 71.2906,
      "lon": -156.7886,
      "country": "USA",
      "temp": -4.99,
      "tempYesterday": -7.381752579274343,
      "tempSwing": 3.941665517647976,
      "windSpeed": 9.77,
      "humidity": 86,
      "feelsLike": -11.99,
      "rainfall24h": 0,
      "pressure": 999
    },
    {
      "name": "Singapore",
      "lat": 1.3521,
      "lon": 103.8198,
      "country": "Singapore",
      "temp": 29.71,
      "tempYesterday": 29.870358459654714,
      "tempSwing": 1.8099999999999987,
      "windSpeed": 2.57,
      "humidity": 78,
      "feelsLike": 36.27,
      "rainfall24h": 0,
      "pressure": 1012
    }
  ],
  "lastUpdate": "2025-11-02T01:38:08.228Z"
}